rdeer/__init__.py
rdeer/client.py
rdeer/common.py
rdeer/info.py
rdeer/server.py
rdeer_service-2.2.0.dist-info/licenses/LICENCE.md
rdeer_service-2.2.0.dist-info/METADATA
rdeer_service-2.2.0.dist-info/WHEEL
rdeer_service-2.2.0.dist-info/entry_points.txt
rdeer_service-2.2.0.dist-info/top_level.txt
rdeer_service-2.2.0.dist-info/RECORD
