Metadata-Version: 2.4
Name: rdeer-service
Version: 2.2.0
Summary: Client-server to handle Reindeer in query mode.
Home-page: https://github.com/Bio2M/rdeer-service
Author: Benoit Guibert
Author-email: benoit.guibert@free.fr
License: GPLv3
Classifier: Development Status :: 3 - Alpha
Classifier: License :: OSI Approved :: GNU General Public License v3 (GPLv3)
Classifier: Operating System :: POSIX :: Linux
Classifier: Programming Language :: Python
Classifier: Natural Language :: English
Classifier: Intended Audience :: Science/Research
Requires-Python: >=3.10
License-File: LICENCE.md
Requires-Dist: packaging
Requires-Dist: requests
Dynamic: author
Dynamic: author-email
Dynamic: classifier
Dynamic: description
Dynamic: description-content-type
Dynamic: home-page
Dynamic: license
Dynamic: license-file
Dynamic: requires-dist
Dynamic: requires-python
Dynamic: summary
